MyCommandCenter/__init__.py
MyCommandCenter/command_center.py
mycommandcenter-0.2.4.dist-info/licenses/LICENSE
mycommandcenter-0.2.4.dist-info/METADATA
mycommandcenter-0.2.4.dist-info/WHEEL
mycommandcenter-0.2.4.dist-info/top_level.txt
mycommandcenter-0.2.4.dist-info/RECORD
