Metadata-Version: 2.4
Name: MyCommandCenter
Version: 0.2.4
Summary: Production-Ready MongoDB & Web Scraping Toolkit
Author-email: Dharmik Vadher <dharmikv972@gmail.com>
License: MIT
Keywords: scraping,mongodb,web-scraping,distributed
Classifier: Programming Language :: Python :: 3
Classifier: License :: OSI Approved :: MIT License
Classifier: Operating System :: OS Independent
Requires-Python: >=3.8
License-File: LICENSE
Dynamic: license-file
